paradance/__init__.py
paradance/dataloader/__init__.py
paradance/dataloader/base.py
paradance/dataloader/load_config.py
paradance/dataloader/load_csv.py
paradance/dataloader/load_excel.py
paradance/evaluation/__init__.py
paradance/evaluation/auc_triple_parameters_evaluator.py
paradance/evaluation/base_calculator.py
paradance/evaluation/base_evaluator.py
paradance/evaluation/calculate_json_formula.py
paradance/evaluation/calculator.py
paradance/evaluation/corrcoef_evaluator.py
paradance/evaluation/cumulative_deviation_evaluator.py
paradance/evaluation/distinct_portfolio_evaluator.py
paradance/evaluation/inverse_pair_evaluator.py
paradance/evaluation/log_mse_evaluator.py
paradance/evaluation/logarithm_pca_calculator.py
paradance/evaluation/mean_evaluator.py
paradance/evaluation/neg_rank_ratio_evaluator.py
paradance/evaluation/portfolio_evaluator.py
paradance/evaluation/proportion_evaluator.py
paradance/evaluation/standard_deviation_evaluator.py
paradance/evaluation/tau_evaluator.py
paradance/evaluation/top_coverage_evaluator.py
paradance/evaluation/woauc_evaluator.py
paradance/evaluation/wuauc_evaluator.py
paradance/optimization/__init__.py
paradance/optimization/base.py
paradance/optimization/construct_weights.py
paradance/optimization/evaluate_targets.py
paradance/optimization/get_processors.py
paradance/optimization/multiple_objective.py
paradance/optimization/optimize_parallel.py
paradance/optimization/save_study.py
paradance/optimization/set_path.py
paradance/optimization/stabilize_mean.py
paradance/pipeline/__init__.py
paradance/pipeline/base.py
paradance/pipeline/classical.py
paradance/pipeline/logarithm_pca.py
paradance/sampling/__init__.py
paradance/sampling/base.py
paradance/sampling/frequency_sampler.py
paradance/sampling/gini_sampler.py
paradance/visualization/__init__.py
paradance/visualization/factor_influence.py
paradance/visualization/portfolio_curve.py
paradance-0.6.7.dist-info/LICENSE
paradance-0.6.7.dist-info/METADATA
paradance-0.6.7.dist-info/WHEEL
paradance-0.6.7.dist-info/RECORD
